<archimate:ArchimateDiagramModel
    xmlns:xsi="http://www.w3.org/2001/XMLSchema-instance"
    xmlns:archimate="http://www.archimatetool.com/archimate"
    name="Scenario 2 in plateau's"
    id="8822dcf3-efc9-4449-ad5c-3bf5e62c9bbb">
  <children
      xsi:type="archimate:DiagramModelArchimateObject"
      id="0698187d-efe3-49c9-83b4-4e263f68fcbe">
    <bounds
        x="48"
        y="12"
        width="229"
        height="565"/>
    <children
        xsi:type="archimate:DiagramModelArchimateObject"
        id="4a5d7483-3b62-4ec8-8fe1-8fdd961cf07c">
      <sourceConnections
          xsi:type="archimate:DiagramModelArchimateConnection"
          id="21b5543e-f8bc-4f4d-bf37-098a650cb30a"
          source="4a5d7483-3b62-4ec8-8fe1-8fdd961cf07c"
          target="ce3b67ae-08e2-4c1c-89e6-6725207e115f">
        <bendpoints
            startY="-75"
            endX="-36"
            endY="81"/>
        <archimateRelationship
            xsi:type="archimate:ServingRelationship"
            href="ServingRelationship_9672c941-44ef-4bb4-9ba1-19f89ac273ce.xml#9672c941-44ef-4bb4-9ba1-19f89ac273ce"/>
      </sourceConnections>
      <bounds
          x="12"
          y="204"
          width="120"
          height="55"/>
      <archimateElement
          xsi:type="archimate:ApplicationComponent"
          href="ApplicationComponent_26c36848.xml#26c36848"/>
    </children>
    <children
        xsi:type="archimate:DiagramModelArchimateObject"
        id="ce3b67ae-08e2-4c1c-89e6-6725207e115f"
        targetConnections="21b5543e-f8bc-4f4d-bf37-098a650cb30a 224537a6-198b-4171-8e38-c44f3df86dce">
      <bounds
          x="48"
          y="48"
          width="120"
          height="55"/>
      <archimateElement
          xsi:type="archimate:BusinessActor"
          href="BusinessActor_3679cb0a-7197-42b7-8f31-6fb6b1b5e360.xml#3679cb0a-7197-42b7-8f31-6fb6b1b5e360"/>
    </children>
    <children
        xsi:type="archimate:DiagramModelArchimateObject"
        id="92207650-9744-40d2-9dfc-590190a5941d">
      <sourceConnections
          xsi:type="archimate:DiagramModelArchimateConnection"
          id="224537a6-198b-4171-8e38-c44f3df86dce"
          source="92207650-9744-40d2-9dfc-590190a5941d"
          target="ce3b67ae-08e2-4c1c-89e6-6725207e115f">
        <bendpoints
            startY="-87"
            endX="36"
            endY="81"/>
        <archimateRelationship
            xsi:type="archimate:ServingRelationship"
            href="ServingRelationship_5936b058-aea5-4341-bd2b-103f6eba5a4a.xml#5936b058-aea5-4341-bd2b-103f6eba5a4a"/>
      </sourceConnections>
      <bounds
          x="84"
          y="132"
          width="120"
          height="55"/>
      <archimateElement
          xsi:type="archimate:ApplicationComponent"
          href="ApplicationComponent_84ba871a.xml#84ba871a"/>
    </children>
    <children
        xsi:type="archimate:DiagramModelArchimateObject"
        id="ff7aeb01-671c-429a-80ff-5db8043ca04b"
        targetConnections="275ebcc9-5c07-4747-bcf2-b98844e5a34a">
      <bounds
          x="48"
          y="492"
          width="120"
          height="55"/>
      <archimateElement
          xsi:type="archimate:BusinessActor"
          href="BusinessActor_f9c152ce.xml#f9c152ce"/>
    </children>
    <children
        xsi:type="archimate:DiagramModelArchimateObject"
        id="cfb3202f-a076-4f71-80f3-9117e89c44ef">
      <sourceConnections
          xsi:type="archimate:DiagramModelArchimateConnection"
          id="275ebcc9-5c07-4747-bcf2-b98844e5a34a"
          source="cfb3202f-a076-4f71-80f3-9117e89c44ef"
          target="ff7aeb01-671c-429a-80ff-5db8043ca04b">
        <archimateRelationship
            xsi:type="archimate:ServingRelationship"
            href="ServingRelationship_fd7f3d31-b6b1-4740-8534-77539db8bd2f.xml#fd7f3d31-b6b1-4740-8534-77539db8bd2f"/>
      </sourceConnections>
      <bounds
          x="48"
          y="420"
          width="120"
          height="55"/>
      <archimateElement
          xsi:type="archimate:ApplicationComponent"
          href="ApplicationComponent_e8540fb6-911e-4db8-9d6d-b3c7bf962d69.xml#e8540fb6-911e-4db8-9d6d-b3c7bf962d69"/>
    </children>
    <archimateElement
        xsi:type="archimate:Plateau"
        href="Plateau_e79eef5f-536a-4f78-9537-374744987369.xml#e79eef5f-536a-4f78-9537-374744987369"/>
  </children>
  <children
      xsi:type="archimate:DiagramModelArchimateObject"
      id="e668a045-5c3f-46e2-b175-6a841512431f">
    <bounds
        x="768"
        y="12"
        width="229"
        height="565"/>
    <children
        xsi:type="archimate:DiagramModelArchimateObject"
        id="ae0659c2-ab39-42c9-86f3-d3c37528a17a"
        targetConnections="67dd59ef-d77d-48fe-84ad-ad01b36d05d3">
      <bounds
          x="48"
          y="48"
          width="120"
          height="55"/>
      <archimateElement
          xsi:type="archimate:BusinessActor"
          href="BusinessActor_3679cb0a-7197-42b7-8f31-6fb6b1b5e360.xml#3679cb0a-7197-42b7-8f31-6fb6b1b5e360"/>
    </children>
    <children
        xsi:type="archimate:DiagramModelArchimateObject"
        id="5d05be92-7eb5-4459-a033-44da6ffe2f76"
        targetConnections="e6709fe4-7ed1-4220-a825-20018812e880 694ff8a8-077f-47b5-badb-7f8852687ef2">
      <sourceConnections
          xsi:type="archimate:DiagramModelArchimateConnection"
          id="67dd59ef-d77d-48fe-84ad-ad01b36d05d3"
          source="5d05be92-7eb5-4459-a033-44da6ffe2f76"
          target="ae0659c2-ab39-42c9-86f3-d3c37528a17a">
        <bendpoints
            startY="-75"
            endX="-36"
            endY="93"/>
        <archimateRelationship
            xsi:type="archimate:ServingRelationship"
            href="ServingRelationship_9672c941-44ef-4bb4-9ba1-19f89ac273ce.xml#9672c941-44ef-4bb4-9ba1-19f89ac273ce"/>
      </sourceConnections>
      <sourceConnections
          xsi:type="archimate:DiagramModelArchimateConnection"
          id="cb77c68a-f13f-4480-a7cd-0d79ccff9843"
          source="5d05be92-7eb5-4459-a033-44da6ffe2f76"
          target="4a44778e-c6cd-4792-8510-28f6217d0d95">
        <bendpoints
            startX="-36"
            startY="117"
            endX="-36"
            endY="-99"/>
        <archimateRelationship
            xsi:type="archimate:FlowRelationship"
            href="FlowRelationship_a7ca108d-9dc1-4da7-ad0f-de04523c679b.xml#a7ca108d-9dc1-4da7-ad0f-de04523c679b"/>
      </sourceConnections>
      <bounds
          x="12"
          y="204"
          width="120"
          height="55"/>
      <archimateElement
          xsi:type="archimate:ApplicationComponent"
          href="ApplicationComponent_26c36848.xml#26c36848"/>
    </children>
    <children
        xsi:type="archimate:DiagramModelArchimateObject"
        id="4a44778e-c6cd-4792-8510-28f6217d0d95"
        targetConnections="cb77c68a-f13f-4480-a7cd-0d79ccff9843">
      <sourceConnections
          xsi:type="archimate:DiagramModelArchimateConnection"
          id="db93d233-0009-411c-bd8c-9212e6f158f7"
          source="4a44778e-c6cd-4792-8510-28f6217d0d95"
          target="bc7a046a-8d51-458e-8a69-2a3ba59491bd">
        <bendpoints
            startY="105"
            endX="36"
            endY="-111"/>
        <archimateRelationship
            xsi:type="archimate:ServingRelationship"
            href="ServingRelationship_fd7f3d31-b6b1-4740-8534-77539db8bd2f.xml#fd7f3d31-b6b1-4740-8534-77539db8bd2f"/>
      </sourceConnections>
      <sourceConnections
          xsi:type="archimate:DiagramModelArchimateConnection"
          id="e6709fe4-7ed1-4220-a825-20018812e880"
          source="4a44778e-c6cd-4792-8510-28f6217d0d95"
          target="5d05be92-7eb5-4459-a033-44da6ffe2f76">
        <bendpoints
            startX="-24"
            startY="-99"
            endX="-24"
            endY="117"/>
        <archimateRelationship
            xsi:type="archimate:FlowRelationship"
            href="FlowRelationship_6290fa83-2f12-408f-8b30-606a748dea63.xml#6290fa83-2f12-408f-8b30-606a748dea63"/>
      </sourceConnections>
      <bounds
          x="12"
          y="420"
          width="120"
          height="55"/>
      <archimateElement
          xsi:type="archimate:ApplicationComponent"
          href="ApplicationComponent_e8540fb6-911e-4db8-9d6d-b3c7bf962d69.xml#e8540fb6-911e-4db8-9d6d-b3c7bf962d69"/>
    </children>
    <children
        xsi:type="archimate:DiagramModelArchimateObject"
        id="bc7a046a-8d51-458e-8a69-2a3ba59491bd"
        targetConnections="db93d233-0009-411c-bd8c-9212e6f158f7">
      <bounds
          x="48"
          y="492"
          width="120"
          height="55"/>
      <archimateElement
          xsi:type="archimate:BusinessActor"
          href="BusinessActor_f9c152ce.xml#f9c152ce"/>
    </children>
    <children
        xsi:type="archimate:DiagramModelArchimateObject"
        id="a7e2aef0-af36-4ae7-a0ff-cda390930adb">
      <bounds
          x="84"
          y="132"
          width="120"
          height="55"/>
      <archimateElement
          xsi:type="archimate:ApplicationComponent"
          href="ApplicationComponent_84ba871a.xml#84ba871a"/>
    </children>
    <children
        xsi:type="archimate:DiagramModelArchimateObject"
        id="e4dcf52f-9d60-4d4b-b672-20c150177b8b">
      <bounds
          x="84"
          y="348"
          width="120"
          height="55"/>
      <archimateElement
          xsi:type="archimate:ApplicationComponent"
          href="ApplicationComponent_5c75bf4e-11d7-4ae5-a807-1d4628f2bc65.xml#5c75bf4e-11d7-4ae5-a807-1d4628f2bc65"/>
    </children>
    <children
        xsi:type="archimate:DiagramModelArchimateObject"
        id="4617ae0b-b7d8-4d3b-a13f-ae0a1dd8b0c2">
      <sourceConnections
          xsi:type="archimate:DiagramModelArchimateConnection"
          id="694ff8a8-077f-47b5-badb-7f8852687ef2"
          source="4617ae0b-b7d8-4d3b-a13f-ae0a1dd8b0c2"
          target="5d05be92-7eb5-4459-a033-44da6ffe2f76">
        <archimateRelationship
            xsi:type="archimate:ServingRelationship"
            href="ServingRelationship_fd5c1f46-4bc9-4fbe-8615-4fb866ea6334.xml#fd5c1f46-4bc9-4fbe-8615-4fb866ea6334"/>
      </sourceConnections>
      <bounds
          x="84"
          y="276"
          width="120"
          height="55"/>
      <archimateElement
          xsi:type="archimate:ApplicationService"
          href="ApplicationService_4ce3809f-d9f0-4193-8484-dde076dd1139.xml#4ce3809f-d9f0-4193-8484-dde076dd1139"/>
    </children>
    <archimateElement
        xsi:type="archimate:Plateau"
        href="Plateau_bfd44114-8b6d-41ce-a9ae-0795b08cbcb4.xml#bfd44114-8b6d-41ce-a9ae-0795b08cbcb4"/>
  </children>
  <children
      xsi:type="archimate:DiagramModelArchimateObject"
      id="ff8660ed-0b88-46c5-9233-33ed87ebb390">
    <bounds
        x="1008"
        y="12"
        width="229"
        height="565"/>
    <children
        xsi:type="archimate:DiagramModelArchimateObject"
        id="ccb76744-04cd-4ff9-8207-4602435f544a">
      <sourceConnections
          xsi:type="archimate:DiagramModelArchimateConnection"
          id="beb25a65-f523-425a-8e3f-6021b1bd5d30"
          source="ccb76744-04cd-4ff9-8207-4602435f544a"
          target="d8cbd165-ec3a-4c7a-be9f-c49c0ae2c269">
        <archimateRelationship
            xsi:type="archimate:ServingRelationship"
            href="ServingRelationship_fd5c1f46-4bc9-4fbe-8615-4fb866ea6334.xml#fd5c1f46-4bc9-4fbe-8615-4fb866ea6334"/>
      </sourceConnections>
      <bounds
          x="84"
          y="276"
          width="120"
          height="55"/>
      <archimateElement
          xsi:type="archimate:ApplicationService"
          href="ApplicationService_4ce3809f-d9f0-4193-8484-dde076dd1139.xml#4ce3809f-d9f0-4193-8484-dde076dd1139"/>
    </children>
    <children
        xsi:type="archimate:DiagramModelArchimateObject"
        id="1b81e89a-f800-48d8-8b61-cfce71e90ecd"
        targetConnections="8eb3a2cd-4e85-4e88-a7c3-7899523bc094">
      <bounds
          x="48"
          y="48"
          width="120"
          height="55"/>
      <archimateElement
          xsi:type="archimate:BusinessActor"
          href="BusinessActor_3679cb0a-7197-42b7-8f31-6fb6b1b5e360.xml#3679cb0a-7197-42b7-8f31-6fb6b1b5e360"/>
    </children>
    <children
        xsi:type="archimate:DiagramModelArchimateObject"
        id="09337e2a-02d9-403a-8818-e7ae04c5c014">
      <bounds
          x="84"
          y="348"
          width="120"
          height="55"/>
      <archimateElement
          xsi:type="archimate:ApplicationComponent"
          href="ApplicationComponent_5c75bf4e-11d7-4ae5-a807-1d4628f2bc65.xml#5c75bf4e-11d7-4ae5-a807-1d4628f2bc65"/>
    </children>
    <children
        xsi:type="archimate:DiagramModelArchimateObject"
        id="d8cbd165-ec3a-4c7a-be9f-c49c0ae2c269"
        targetConnections="64fe179e-6854-42f1-9d9c-13e53b640afa beb25a65-f523-425a-8e3f-6021b1bd5d30">
      <sourceConnections
          xsi:type="archimate:DiagramModelArchimateConnection"
          id="585c0665-8710-4639-a61a-fe220f038e01"
          source="d8cbd165-ec3a-4c7a-be9f-c49c0ae2c269"
          target="8094d83e-f15e-4ac6-9d0f-c88ff47b9b03">
        <bendpoints
            startX="-36"
            startY="105"
            endX="-36"
            endY="-111"/>
        <archimateRelationship
            xsi:type="archimate:FlowRelationship"
            href="FlowRelationship_a7ca108d-9dc1-4da7-ad0f-de04523c679b.xml#a7ca108d-9dc1-4da7-ad0f-de04523c679b"/>
      </sourceConnections>
      <sourceConnections
          xsi:type="archimate:DiagramModelArchimateConnection"
          id="8eb3a2cd-4e85-4e88-a7c3-7899523bc094"
          source="d8cbd165-ec3a-4c7a-be9f-c49c0ae2c269"
          target="1b81e89a-f800-48d8-8b61-cfce71e90ecd">
        <archimateRelationship
            xsi:type="archimate:ServingRelationship"
            href="ServingRelationship_9672c941-44ef-4bb4-9ba1-19f89ac273ce.xml#9672c941-44ef-4bb4-9ba1-19f89ac273ce"/>
      </sourceConnections>
      <bounds
          x="12"
          y="204"
          width="120"
          height="55"/>
      <archimateElement
          xsi:type="archimate:ApplicationComponent"
          href="ApplicationComponent_26c36848.xml#26c36848"/>
    </children>
    <children
        xsi:type="archimate:DiagramModelArchimateObject"
        id="cc551fc3-b861-4617-94f4-73e8fde95612"
        targetConnections="eaf160fa-1314-4f3b-b8b4-d958d25e2800">
      <bounds
          x="48"
          y="492"
          width="120"
          height="55"/>
      <archimateElement
          xsi:type="archimate:BusinessActor"
          href="BusinessActor_f9c152ce.xml#f9c152ce"/>
    </children>
    <children
        xsi:type="archimate:DiagramModelArchimateObject"
        id="8094d83e-f15e-4ac6-9d0f-c88ff47b9b03"
        targetConnections="585c0665-8710-4639-a61a-fe220f038e01">
      <sourceConnections
          xsi:type="archimate:DiagramModelArchimateConnection"
          id="eaf160fa-1314-4f3b-b8b4-d958d25e2800"
          source="8094d83e-f15e-4ac6-9d0f-c88ff47b9b03"
          target="cc551fc3-b861-4617-94f4-73e8fde95612">
        <bendpoints
            startY="105"
            endX="36"
            endY="-111"/>
        <archimateRelationship
            xsi:type="archimate:ServingRelationship"
            href="ServingRelationship_fd7f3d31-b6b1-4740-8534-77539db8bd2f.xml#fd7f3d31-b6b1-4740-8534-77539db8bd2f"/>
      </sourceConnections>
      <sourceConnections
          xsi:type="archimate:DiagramModelArchimateConnection"
          id="64fe179e-6854-42f1-9d9c-13e53b640afa"
          source="8094d83e-f15e-4ac6-9d0f-c88ff47b9b03"
          target="d8cbd165-ec3a-4c7a-be9f-c49c0ae2c269">
        <bendpoints
            startX="-24"
            startY="-111"
            endX="-24"
            endY="105"/>
        <archimateRelationship
            xsi:type="archimate:FlowRelationship"
            href="FlowRelationship_6290fa83-2f12-408f-8b30-606a748dea63.xml#6290fa83-2f12-408f-8b30-606a748dea63"/>
      </sourceConnections>
      <bounds
          x="12"
          y="420"
          width="120"
          height="55"/>
      <archimateElement
          xsi:type="archimate:ApplicationComponent"
          href="ApplicationComponent_e8540fb6-911e-4db8-9d6d-b3c7bf962d69.xml#e8540fb6-911e-4db8-9d6d-b3c7bf962d69"/>
    </children>
    <archimateElement
        xsi:type="archimate:Plateau"
        href="Plateau_26faafe2-b546-4b05-b380-b3e2efce32b8.xml#26faafe2-b546-4b05-b380-b3e2efce32b8"/>
  </children>
  <children
      xsi:type="archimate:DiagramModelArchimateObject"
      id="6b162738-81ad-48a9-969e-7397f7414040">
    <bounds
        x="288"
        y="12"
        width="229"
        height="565"/>
    <children
        xsi:type="archimate:DiagramModelArchimateObject"
        id="7d206cd5-6a07-48ae-8351-369af0e83be1"
        targetConnections="8e987fc2-7cad-4715-8ded-df357d54931d 076e96cd-4aaf-4090-9853-25e896ccfafe">
      <bounds
          x="48"
          y="48"
          width="120"
          height="55"/>
      <archimateElement
          xsi:type="archimate:BusinessActor"
          href="BusinessActor_3679cb0a-7197-42b7-8f31-6fb6b1b5e360.xml#3679cb0a-7197-42b7-8f31-6fb6b1b5e360"/>
    </children>
    <children
        xsi:type="archimate:DiagramModelArchimateObject"
        id="8bcd2365-77d2-476d-b233-e50ee1decef8"
        targetConnections="a30fbfee-a131-4d40-baac-64c7dbae0691">
      <bounds
          x="48"
          y="492"
          width="120"
          height="55"/>
      <archimateElement
          xsi:type="archimate:BusinessActor"
          href="BusinessActor_f9c152ce.xml#f9c152ce"/>
    </children>
    <children
        xsi:type="archimate:DiagramModelArchimateObject"
        id="92bc97ed-5b1b-4582-b227-46cca7e6e2bc"
        targetConnections="43584640-a264-4775-800a-b69e2f899ce7">
      <sourceConnections
          xsi:type="archimate:DiagramModelArchimateConnection"
          id="8e987fc2-7cad-4715-8ded-df357d54931d"
          source="92bc97ed-5b1b-4582-b227-46cca7e6e2bc"
          target="7d206cd5-6a07-48ae-8351-369af0e83be1">
        <bendpoints
            startY="-75"
            endX="-36"
            endY="81"/>
        <archimateRelationship
            xsi:type="archimate:ServingRelationship"
            href="ServingRelationship_9672c941-44ef-4bb4-9ba1-19f89ac273ce.xml#9672c941-44ef-4bb4-9ba1-19f89ac273ce"/>
      </sourceConnections>
      <sourceConnections
          xsi:type="archimate:DiagramModelArchimateConnection"
          id="89c25f91-8973-4a19-947e-8e09b675526c"
          source="92bc97ed-5b1b-4582-b227-46cca7e6e2bc"
          target="05af70c9-addc-408c-8a63-5a81e3dafa41">
        <bendpoints
            startX="-24"
            startY="117"
            endX="-24"
            endY="-99"/>
        <archimateRelationship
            xsi:type="archimate:FlowRelationship"
            href="FlowRelationship_a7ca108d-9dc1-4da7-ad0f-de04523c679b.xml#a7ca108d-9dc1-4da7-ad0f-de04523c679b"/>
      </sourceConnections>
      <bounds
          x="12"
          y="204"
          width="120"
          height="55"/>
      <archimateElement
          xsi:type="archimate:ApplicationComponent"
          href="ApplicationComponent_26c36848.xml#26c36848"/>
    </children>
    <children
        xsi:type="archimate:DiagramModelArchimateObject"
        id="67f13a41-d18e-4f7e-9f42-3086910a8b0f">
      <sourceConnections
          xsi:type="archimate:DiagramModelArchimateConnection"
          id="076e96cd-4aaf-4090-9853-25e896ccfafe"
          source="67f13a41-d18e-4f7e-9f42-3086910a8b0f"
          target="7d206cd5-6a07-48ae-8351-369af0e83be1">
        <bendpoints
            startY="-39"
            endX="36"
            endY="45"/>
        <archimateRelationship
            xsi:type="archimate:ServingRelationship"
            href="ServingRelationship_5936b058-aea5-4341-bd2b-103f6eba5a4a.xml#5936b058-aea5-4341-bd2b-103f6eba5a4a"/>
      </sourceConnections>
      <bounds
          x="84"
          y="132"
          width="120"
          height="55"/>
      <archimateElement
          xsi:type="archimate:ApplicationComponent"
          href="ApplicationComponent_84ba871a.xml#84ba871a"/>
    </children>
    <children
        xsi:type="archimate:DiagramModelArchimateObject"
        id="05af70c9-addc-408c-8a63-5a81e3dafa41"
        targetConnections="89c25f91-8973-4a19-947e-8e09b675526c">
      <sourceConnections
          xsi:type="archimate:DiagramModelArchimateConnection"
          id="a30fbfee-a131-4d40-baac-64c7dbae0691"
          source="05af70c9-addc-408c-8a63-5a81e3dafa41"
          target="8bcd2365-77d2-476d-b233-e50ee1decef8">
        <archimateRelationship
            xsi:type="archimate:ServingRelationship"
            href="ServingRelationship_fd7f3d31-b6b1-4740-8534-77539db8bd2f.xml#fd7f3d31-b6b1-4740-8534-77539db8bd2f"/>
      </sourceConnections>
      <sourceConnections
          xsi:type="archimate:DiagramModelArchimateConnection"
          id="43584640-a264-4775-800a-b69e2f899ce7"
          source="05af70c9-addc-408c-8a63-5a81e3dafa41"
          target="92bc97ed-5b1b-4582-b227-46cca7e6e2bc">
        <bendpoints
            startX="-12"
            startY="-111"
            endX="-12"
            endY="105"/>
        <archimateRelationship
            xsi:type="archimate:FlowRelationship"
            href="FlowRelationship_6290fa83-2f12-408f-8b30-606a748dea63.xml#6290fa83-2f12-408f-8b30-606a748dea63"/>
      </sourceConnections>
      <bounds
          x="12"
          y="420"
          width="120"
          height="55"/>
      <archimateElement
          xsi:type="archimate:ApplicationComponent"
          href="ApplicationComponent_e8540fb6-911e-4db8-9d6d-b3c7bf962d69.xml#e8540fb6-911e-4db8-9d6d-b3c7bf962d69"/>
    </children>
    <archimateElement
        xsi:type="archimate:Plateau"
        href="Plateau_81c87eba-76df-4c88-96c1-550181ddf0a5.xml#81c87eba-76df-4c88-96c1-550181ddf0a5"/>
  </children>
  <children
      xsi:type="archimate:DiagramModelArchimateObject"
      id="83abe27c-73b7-4847-94c9-2e0db3b382a4">
    <bounds
        x="528"
        y="12"
        width="229"
        height="565"/>
    <children
        xsi:type="archimate:DiagramModelArchimateObject"
        id="11efda6c-0c43-4f12-a382-8b8dc79171c1"
        targetConnections="040393f9-eef0-4cff-b21e-c3b71feb3f40">
      <sourceConnections
          xsi:type="archimate:DiagramModelArchimateConnection"
          id="35195818-374b-490e-bebc-4cfe4b4d26f5"
          source="11efda6c-0c43-4f12-a382-8b8dc79171c1"
          target="3601c700-fa75-4809-8481-0c0cde6fd5cc">
        <archimateRelationship
            xsi:type="archimate:ServingRelationship"
            href="ServingRelationship_fd7f3d31-b6b1-4740-8534-77539db8bd2f.xml#fd7f3d31-b6b1-4740-8534-77539db8bd2f"/>
      </sourceConnections>
      <sourceConnections
          xsi:type="archimate:DiagramModelArchimateConnection"
          id="c029ef09-17dc-4058-b34b-e9967e7f8724"
          source="11efda6c-0c43-4f12-a382-8b8dc79171c1"
          target="54bc3d7e-455f-4913-8e83-38f0334ad217">
        <bendpoints
            startX="-36"
            startY="-111"
            endY="105"/>
        <archimateRelationship
            xsi:type="archimate:FlowRelationship"
            href="FlowRelationship_6290fa83-2f12-408f-8b30-606a748dea63.xml#6290fa83-2f12-408f-8b30-606a748dea63"/>
      </sourceConnections>
      <bounds
          x="12"
          y="420"
          width="120"
          height="55"/>
      <archimateElement
          xsi:type="archimate:ApplicationComponent"
          href="ApplicationComponent_e8540fb6-911e-4db8-9d6d-b3c7bf962d69.xml#e8540fb6-911e-4db8-9d6d-b3c7bf962d69"/>
    </children>
    <children
        xsi:type="archimate:DiagramModelArchimateObject"
        id="3601c700-fa75-4809-8481-0c0cde6fd5cc"
        targetConnections="35195818-374b-490e-bebc-4cfe4b4d26f5">
      <bounds
          x="48"
          y="492"
          width="120"
          height="55"/>
      <archimateElement
          xsi:type="archimate:BusinessActor"
          href="BusinessActor_f9c152ce.xml#f9c152ce"/>
    </children>
    <children
        xsi:type="archimate:DiagramModelArchimateObject"
        id="d60b986b-2ab1-42fe-85af-e77675109bf7"
        targetConnections="c8ad1006-ccbe-4a6b-8978-84dca1aaf6fe 2b47dda1-0ac9-45a2-9b0d-8a0c5317ebe7">
      <bounds
          x="48"
          y="48"
          width="120"
          height="55"/>
      <archimateElement
          xsi:type="archimate:BusinessActor"
          href="BusinessActor_3679cb0a-7197-42b7-8f31-6fb6b1b5e360.xml#3679cb0a-7197-42b7-8f31-6fb6b1b5e360"/>
    </children>
    <children
        xsi:type="archimate:DiagramModelArchimateObject"
        id="54bc3d7e-455f-4913-8e83-38f0334ad217"
        targetConnections="c029ef09-17dc-4058-b34b-e9967e7f8724 5a370e69-d1db-41b0-bd21-e735a7772739">
      <sourceConnections
          xsi:type="archimate:DiagramModelArchimateConnection"
          id="040393f9-eef0-4cff-b21e-c3b71feb3f40"
          source="54bc3d7e-455f-4913-8e83-38f0334ad217"
          target="11efda6c-0c43-4f12-a382-8b8dc79171c1">
        <bendpoints
            startX="-12"
            startY="117"
            endX="-48"
            endY="-99"/>
        <archimateRelationship
            xsi:type="archimate:FlowRelationship"
            href="FlowRelationship_a7ca108d-9dc1-4da7-ad0f-de04523c679b.xml#a7ca108d-9dc1-4da7-ad0f-de04523c679b"/>
      </sourceConnections>
      <sourceConnections
          xsi:type="archimate:DiagramModelArchimateConnection"
          id="c8ad1006-ccbe-4a6b-8978-84dca1aaf6fe"
          source="54bc3d7e-455f-4913-8e83-38f0334ad217"
          target="d60b986b-2ab1-42fe-85af-e77675109bf7">
        <bendpoints
            startY="-75"
            endX="-36"
            endY="81"/>
        <archimateRelationship
            xsi:type="archimate:ServingRelationship"
            href="ServingRelationship_9672c941-44ef-4bb4-9ba1-19f89ac273ce.xml#9672c941-44ef-4bb4-9ba1-19f89ac273ce"/>
      </sourceConnections>
      <bounds
          x="12"
          y="204"
          width="120"
          height="55"/>
      <archimateElement
          xsi:type="archimate:ApplicationComponent"
          href="ApplicationComponent_26c36848.xml#26c36848"/>
    </children>
    <children
        xsi:type="archimate:DiagramModelArchimateObject"
        id="f82ef214-9ab3-4d6a-b16c-1276bb06c458">
      <sourceConnections
          xsi:type="archimate:DiagramModelArchimateConnection"
          id="2b47dda1-0ac9-45a2-9b0d-8a0c5317ebe7"
          source="f82ef214-9ab3-4d6a-b16c-1276bb06c458"
          target="d60b986b-2ab1-42fe-85af-e77675109bf7">
        <bendpoints
            startX="-12"
            startY="-39"
            endX="24"
            endY="45"/>
        <archimateRelationship
            xsi:type="archimate:ServingRelationship"
            href="ServingRelationship_5936b058-aea5-4341-bd2b-103f6eba5a4a.xml#5936b058-aea5-4341-bd2b-103f6eba5a4a"/>
      </sourceConnections>
      <bounds
          x="84"
          y="132"
          width="120"
          height="55"/>
      <archimateElement
          xsi:type="archimate:ApplicationComponent"
          href="ApplicationComponent_84ba871a.xml#84ba871a"/>
    </children>
    <children
        xsi:type="archimate:DiagramModelArchimateObject"
        id="c2affcda-a1f7-45dd-bd4d-071a02c38e25">
      <sourceConnections
          xsi:type="archimate:DiagramModelArchimateConnection"
          id="5a370e69-d1db-41b0-bd21-e735a7772739"
          source="c2affcda-a1f7-45dd-bd4d-071a02c38e25"
          target="54bc3d7e-455f-4913-8e83-38f0334ad217">
        <archimateRelationship
            xsi:type="archimate:ServingRelationship"
            href="ServingRelationship_fd5c1f46-4bc9-4fbe-8615-4fb866ea6334.xml#fd5c1f46-4bc9-4fbe-8615-4fb866ea6334"/>
      </sourceConnections>
      <bounds
          x="84"
          y="276"
          width="120"
          height="55"/>
      <archimateElement
          xsi:type="archimate:ApplicationService"
          href="ApplicationService_4ce3809f-d9f0-4193-8484-dde076dd1139.xml#4ce3809f-d9f0-4193-8484-dde076dd1139"/>
    </children>
    <children
        xsi:type="archimate:DiagramModelArchimateObject"
        id="f9e53615-2e71-4795-9455-68ca49532999">
      <bounds
          x="84"
          y="348"
          width="120"
          height="55"/>
      <archimateElement
          xsi:type="archimate:ApplicationComponent"
          href="ApplicationComponent_5c75bf4e-11d7-4ae5-a807-1d4628f2bc65.xml#5c75bf4e-11d7-4ae5-a807-1d4628f2bc65"/>
    </children>
    <archimateElement
        xsi:type="archimate:Plateau"
        href="Plateau_5d90c124-982e-4338-9714-b2a7e55b0c28.xml#5d90c124-982e-4338-9714-b2a7e55b0c28"/>
  </children>
</archimate:ArchimateDiagramModel>
